Workbook

Sheet April 2026 Allocation
A1: Armada Capital Group LLP — April 2026 Allocation
A2: Scenario B: JJNA $8M April capital call active during April. Yellow cells = inputs.
A4: INPUTS | B4: Value | C4: Format | D4: Source / Notes
A5: Bliss Investments LLC — beginning capital | B5: 508472 | C5: $ | D5: March 31 PCAS ending balance
A6: JJNA, LLC — March accrual carryforward | B6: 20000 | C6: $ | D6: March 31 PCAS ending balance
A7: JJNA, LLC — April capital call | B7: 8000000 | C7: $ | D7: $8M JJNA close formally lands in April (was deployed in March as 'received in advance')
A8: Gross monthly return | B8: 0.057 | C8: % | D8: April 2026 gross fund return
A10: BEGINNING CAPITAL | B10: Amount | C10: % of Total | D10: Detail
A11: Bliss Investments LLC | B11: =B5 | C11: =B11/$B$13 | D11: Carry-forward from March
A12: JJNA, LLC (carryforward + April call) | B12: =B6+B7 | C12: =B12/$B$13 | D12: $20K accrual + $8M April capital call
A13: Total LP Capital | B13: =B11+B12 | C13: 1
A15: GROSS PROFIT | B15: Amount | C15: % of Capital | D15: Formula
A16: Gross monthly return × Total LP Capital | B16: =B13*B8 | C16: =B8 | D16: =$8,528,472 × 5.700%
A18: WATERFALL | B18: Amount | C18: % of Gross | D18: Effective % of Capital
A19: Traders / TruQuant | B19: =B16*0.18 | C19: 0.18 | D19: =B19/B13
A20: Armada Capital Group (82%) | B20: =B16*0.82 | C20: 0.82 | D20: =B20/B13
A21: ↳ LPs (70% of ACG = 57.4% of gross) | B21: =B20*0.70 | C21: =0.82*0.70 | D21: =B21/B13
A22: ↳ GP / Innovations (30% of ACG = 24.6% of gross) | B22: =B20*0.30 | C22: =0.82*0.30 | D22: =B22/B13
A23: Total (must = Gross Profit) | B23: =B19+B21+B22 | C23: 1 | D23: =B23/B13
A25: LP ALLOCATION (pro-rata by beginning balance) | B25: Amount | C25: Pro-rata % | D25: Effective % on capital
A26: Bliss Investments LLC | B26: =$B$21*C26 | C26: =B11/$B$13 | D26: =B26/B11
A27: JJNA, LLC | B27: =$B$21*C27 | C27: =B12/$B$13 | D27: =B27/B12
A28: Total LP | B28: =B26+B27 | C28: 1
A30: GP DISTRIBUTION — Armada Innovations LLC | B30: Amount | C30: Member Share | D30: Role
A31: Nairne | B31: =$B$22*C31 | C31: 0.6 | D31: Managing Member
A32: Alec | B32: =$B$22*C32 | C32: 0.395 | D32: Capital Relations
A33: Chris | B33: =$B$22*C33 | C33: 0.005 | D33: Member
A34: Total GP | B34: =B31+B32+B33 | C34: =C31+C32+C33
A36: APRIL ENDING CAPITAL (= May 1 beginning) | B36: Amount | C36: Change
A37: Bliss Investments LLC | B37: =B11+B26 | C37: =B26
A38: JJNA, LLC | B38: =B12+B27 | C38: =B27
A39: Total LP Ending Capital | B39: =B37+B38 | C39: =B28

Sheet Who Gets What
A1: April 2026 — One-Page Summary
A3: Recipient | B3: Bucket | C3: % of Gross | D3: April Cut | E3: Notes
A4: Bliss Investments LLC | B4: LP | C4: =D4/$D$13 | D4: ='April 2026 Allocation'!B26 | E4: 96.22% of LP slice
A5: JJNA, LLC | B5: LP | C5: =D5/$D$13 | D5: ='April 2026 Allocation'!B27 | E5: 3.78% of LP slice
A6: TruQuant (traders) | B6: Trader | C6: 0.18 | D6: ='April 2026 Allocation'!B19 | E6: 18% straight off the top
A7: Nairne | B7: GP | C7: =D7/$D$13 | D7: ='April 2026 Allocation'!B31 | E7: 60% of Innovations LLC
A8: Alec | B8: GP | C8: =D8/$D$13 | D8: ='April 2026 Allocation'!B32 | E8: 39.5% of Innovations LLC
A9: Chris | B9: GP | C9: =D9/$D$13 | D9: ='April 2026 Allocation'!B33 | E9: 0.5% of Innovations LLC
A13: TOTAL GROSS PROFIT | C13: 1 | D13: =SUM(D4:D9) | E13: ='April 2026 Allocation'!B16
A15: Tie-out (D13 must equal E13): | B15: =IF(ROUND(D13-E13,2)=0,"✓ tied","✗ MISMATCH")

Sheet Brokerage Attribution
A1: Brokerage Account Attribution Flow — May 1, 2026
A2: Where every dollar in the brokerage came from and where it sits today.
A4: Party | B4: Capital Contributed | C4: Mar 31 Balance (= Apr 1 Beg) | D4: + Apr Activity (net of fees) | E4: + May Wire (advance) | F4: Current Balance (May 1)
A5: Bliss Investments LLC | B5: 500000 | C5: 508472 | D5: 16636.19 | E5: 0 | F5: 525108.19
A6: JJNA, LLC | B6: 8000000 | C6: 8020000 | D6: 262398.36 | E6: 0 | F6: 8282398.4
A7: New May Investors | B7: 1499728 | C7: 0 | D7: 0 | E7: 1499728 | F7: 1499728
A8: TruQuant (accrued payable) | B8: 0 | C8: 0 | D8: 87502.12 | E8: 0 | F8: 87502.12
A9: Innovations GP (accrued) | B9: 0 | C9: 3720 | D9: 119586.23 | E9: 0 | F9: 123306.23
A10: Bank-fee cash carry | B10: 0 | C10: -135.9 | D10: 0 | E10: 0 | F10: -135.9
A11: TOTAL ATTRIBUTED | B11: =SUM(B5:B10) | C11: =SUM(C5:C10) | D11: =SUM(D5:D10) | E11: =SUM(E5:E10) | F11: =SUM(F5:F10)
A12: Brokerage actual (live) | F12: 10519780
A13: LEFTOVER (≈1 day fund growth) | F13: =F12-F11
A15: Tie-out: Mar 31 base + Apr activity + May advance = Current Balance
A16: =C11&" + "&D11&" + "&E11&" = "&F11
